JiyuEthereumDeWuzhongLianHuanjingDajianFangshi/README.md
JiyuEthereumDeWuzhongLianHuanjingDajianFangshi/__init__.py
JiyuEthereumDeWuzhongLianHuanjingDajianFangshi/__main__.py
JiyuEthereumDeWuzhongLianHuanjingDajianFangshi/file.epub
JiyuEthereumDeWuzhongLianHuanjingDajianFangshi/index.html
JiyuEthereumDeWuzhongLianHuanjingDajianFangshi/css/__init__.py
JiyuEthereumDeWuzhongLianHuanjingDajianFangshi/css/annotations.css
JiyuEthereumDeWuzhongLianHuanjingDajianFangshi/css/main.css
JiyuEthereumDeWuzhongLianHuanjingDajianFangshi/css/normalize.css
JiyuEthereumDeWuzhongLianHuanjingDajianFangshi/css/popup.css
JiyuEthereumDeWuzhongLianHuanjingDajianFangshi/font/__init__.py
JiyuEthereumDeWuzhongLianHuanjingDajianFangshi/font/fontello.eot
JiyuEthereumDeWuzhongLianHuanjingDajianFangshi/font/fontello.svg
JiyuEthereumDeWuzhongLianHuanjingDajianFangshi/font/fontello.ttf
JiyuEthereumDeWuzhongLianHuanjingDajianFangshi/font/fontello.woff
JiyuEthereumDeWuzhongLianHuanjingDajianFangshi/img/__init__.py
JiyuEthereumDeWuzhongLianHuanjingDajianFangshi/img/annotator-glyph-sprite.png
JiyuEthereumDeWuzhongLianHuanjingDajianFangshi/img/annotator-icon-sprite.png
JiyuEthereumDeWuzhongLianHuanjingDajianFangshi/img/apple-touch-icon.png
JiyuEthereumDeWuzhongLianHuanjingDajianFangshi/img/cancelfullscreen.png
JiyuEthereumDeWuzhongLianHuanjingDajianFangshi/img/close.png
JiyuEthereumDeWuzhongLianHuanjingDajianFangshi/img/fullscreen.png
JiyuEthereumDeWuzhongLianHuanjingDajianFangshi/img/loader.gif
JiyuEthereumDeWuzhongLianHuanjingDajianFangshi/img/menu-icon.png
JiyuEthereumDeWuzhongLianHuanjingDajianFangshi/img/save.png
JiyuEthereumDeWuzhongLianHuanjingDajianFangshi/img/saved.png
JiyuEthereumDeWuzhongLianHuanjingDajianFangshi/img/settings-s.png
JiyuEthereumDeWuzhongLianHuanjingDajianFangshi/img/settings.png
JiyuEthereumDeWuzhongLianHuanjingDajianFangshi/img/star.png
JiyuEthereumDeWuzhongLianHuanjingDajianFangshi/js/__init__.py
JiyuEthereumDeWuzhongLianHuanjingDajianFangshi/js/epub.js
jiyu_ethereum_de_wuzhong_lian_huanjing_dajian_fangshi-2024.3.4.0.dist-info/METADATA
jiyu_ethereum_de_wuzhong_lian_huanjing_dajian_fangshi-2024.3.4.0.dist-info/WHEEL
jiyu_ethereum_de_wuzhong_lian_huanjing_dajian_fangshi-2024.3.4.0.dist-info/entry_points.txt
jiyu_ethereum_de_wuzhong_lian_huanjing_dajian_fangshi-2024.3.4.0.dist-info/top_level.txt
jiyu_ethereum_de_wuzhong_lian_huanjing_dajian_fangshi-2024.3.4.0.dist-info/RECORD
